m3u8dl/__init__.py
m3u8dl/__main__.py
m3u8dl/core/__init__.py
m3u8dl/core/download_process.py
m3u8dl/core/m3u8dl.py
m3u8dl/core/producer_server_process.py
m3u8dl/core/progressbar.py
m3u8dl/core/video_handling_process.py
m3u8dl/core/common/__init__.py
m3u8dl/core/common/base.py
m3u8dl/core/common/constants.py
m3u8dl/core/m3u8lib/__init__.py
m3u8dl/core/m3u8lib/parser.py
m3u8dl/core/videolib/__init__.py
m3u8dl/core/videolib/convertor.py
m3u8dl/core/weblib/__init__.py
m3u8dl/core/weblib/fetch.py
m3u8dl/core/weblib/parse.py
m3u8dl-0.5.2.dist-info/LICENSE
m3u8dl-0.5.2.dist-info/METADATA
m3u8dl-0.5.2.dist-info/WHEEL
m3u8dl-0.5.2.dist-info/entry_points.txt
m3u8dl-0.5.2.dist-info/top_level.txt
m3u8dl-0.5.2.dist-info/RECORD
