Metadata-Version: 2.1
Name: m3u8dl
Version: 0.5.2
Summary: m3u8 playlist downloader
Home-page: https://github.com/excalibur-kvrv/m3u8-dl
Author: Kevin Rohan Vaz
Author-email: excalibur.krv@gmail.com
Maintainer: Kevin Rohan Vaz
Maintainer-email: excalibur.krv@gmail.com
License: UNKNOWN
Platform: UNKNOWN
Classifier: Programming Language :: Python :: 3
Classifier: License :: OSI Approved :: MIT License
Classifier: Operating System :: OS Independent
Requires-Python: >=3.6
License-File: LICENSE
Requires-Dist: hyper (==0.7.0)
Requires-Dist: requests (==2.26.0)
Requires-Dist: tqdm (==4.62.3)
